mbta_gtfs_sqlite/__init__.py
mbta_gtfs_sqlite/archive.py
mbta_gtfs_sqlite/build.py
mbta_gtfs_sqlite/compact.py
mbta_gtfs_sqlite/feed.py
mbta_gtfs_sqlite/ingest.py
mbta_gtfs_sqlite/models/__init__.py
mbta_gtfs_sqlite/models/agency.py
mbta_gtfs_sqlite/models/base.py
mbta_gtfs_sqlite/models/calendar.py
mbta_gtfs_sqlite/models/calendar_attributes.py
mbta_gtfs_sqlite/models/calendar_dates.py
mbta_gtfs_sqlite/models/feed_info.py
mbta_gtfs_sqlite/models/lines.py
mbta_gtfs_sqlite/models/route_patterns.py
mbta_gtfs_sqlite/models/routes.py
mbta_gtfs_sqlite/models/shapes.py
mbta_gtfs_sqlite/models/stop_times.py
mbta_gtfs_sqlite/models/stops.py
mbta_gtfs_sqlite/models/transfers.py
mbta_gtfs_sqlite/models/trips.py
mbta_gtfs_sqlite/reader.py
mbta_gtfs_sqlite/session.py
mbta_gtfs_sqlite/utils/decorators.py
mbta_gtfs_sqlite/utils/enum.py
mbta_gtfs_sqlite/utils/indexes.py
mbta_gtfs_sqlite/utils/time.py
mbta_gtfs_sqlite-1.1.2.dist-info/METADATA
mbta_gtfs_sqlite-1.1.2.dist-info/WHEEL
mbta_gtfs_sqlite-1.1.2.dist-info/RECORD
