Metadata-Version: 2.3
Name: mbta-gtfs-sqlite
Version: 1.1.2
Summary: Query the MBTA's static GTFS feeds using sqlite
Author: Ian Reynolds
Author-email: ireynolds@transitmatters.info
Requires-Python: >=3.8,<4.0
Classifier: Programming Language :: Python :: 3
Classifier: Programming Language :: Python :: 3.8
Classifier: Programming Language :: Python :: 3.9
Classifier: Programming Language :: Python :: 3.10
Classifier: Programming Language :: Python :: 3.11
Classifier: Programming Language :: Python :: 3.12
Classifier: Programming Language :: Python :: 3.13
Requires-Dist: SQLAlchemy (>=2.0.7,<3.0.0)
Requires-Dist: more-itertools (>=10.1.0,<11.0.0)
Requires-Dist: requests (>=2.28.2,<3.0.0)
